rai_bench/__init__.py
rai_bench/agents.py
rai_bench/base_benchmark.py
rai_bench/docs/imgs/tool_calling_agent_valid_schema.png
rai_bench/docs/tool_calling_agent_benchmark.md
rai_bench/examples/benchmarking_models.py
rai_bench/examples/dual_agent.py
rai_bench/examples/manipulation_o3de.py
rai_bench/examples/tool_calling_agent.py
rai_bench/examples/visualise_streamlit.py
rai_bench/manipulation_o3de/__init__.py
rai_bench/manipulation_o3de/benchmark.py
rai_bench/manipulation_o3de/interfaces.py
rai_bench/manipulation_o3de/predefined/configs/1a.yaml
rai_bench/manipulation_o3de/predefined/configs/1a_1t.yaml
rai_bench/manipulation_o3de/predefined/configs/1a_2bc.yaml
rai_bench/manipulation_o3de/predefined/configs/1bc_1rc_1yc.yaml
rai_bench/manipulation_o3de/predefined/configs/1carrot.yaml
rai_bench/manipulation_o3de/predefined/configs/1carrot_1a_1t_1bc_1corn.yaml
rai_bench/manipulation_o3de/predefined/configs/1carrot_1a_2t_1bc_1rc_3yc_stacked.yaml
rai_bench/manipulation_o3de/predefined/configs/1carrot_1bc.yaml
rai_bench/manipulation_o3de/predefined/configs/1carrot_1corn.yaml
rai_bench/manipulation_o3de/predefined/configs/1carrot_1t_1rc.yaml
rai_bench/manipulation_o3de/predefined/configs/1rc.yaml
rai_bench/manipulation_o3de/predefined/configs/1rc_2bc_3yc.yaml
rai_bench/manipulation_o3de/predefined/configs/1t.yaml
rai_bench/manipulation_o3de/predefined/configs/1yc.yaml
rai_bench/manipulation_o3de/predefined/configs/1yc_1rc.yaml
rai_bench/manipulation_o3de/predefined/configs/2a_1bc.yaml
rai_bench/manipulation_o3de/predefined/configs/2a_1c_2rc.yaml
rai_bench/manipulation_o3de/predefined/configs/2carrots_1a_1t_1bc_1rc_1yc_1corn.yaml
rai_bench/manipulation_o3de/predefined/configs/2carrots_2a.yaml
rai_bench/manipulation_o3de/predefined/configs/2rc.yaml
rai_bench/manipulation_o3de/predefined/configs/2rc_3bc_4yc_stacked.yaml
rai_bench/manipulation_o3de/predefined/configs/2t.yaml
rai_bench/manipulation_o3de/predefined/configs/2t_3a_1corn_2rc.yaml
rai_bench-0.1.2.dist-info/METADATA
rai_bench-0.1.2.dist-info/WHEEL
rai_bench-0.1.2.dist-info/RECORD
