Metadata-Version: 2.3
Name: rai-bench
Version: 0.1.2
Summary: Package for running and creating benchmarks.
Author: Jakub Matejczyk
Author-email: jakub.matejczyk@robotec.ai
Requires-Python: >=3.10,<4.0
Classifier: Programming Language :: Python :: 3
Classifier: Programming Language :: Python :: 3.10
Classifier: Programming Language :: Python :: 3.11
Classifier: Programming Language :: Python :: 3.12
Classifier: Programming Language :: Python :: 3.13
Requires-Dist: inflect (==7.5.0)
Requires-Dist: plotly (>=6.0.1,<7.0.0)
Requires-Dist: rai_core (>=2.0.0.a2,<3.0.0)
Requires-Dist: rai_sim (>=0.0.2,<1.0.0)
